gcover/__init__.py
gcover/_version.py
gcover/config.py
gcover/bridge/__init__.py
gcover/bridge/sde.py
gcover/cli/__init__.py
gcover/cli/main.py
gcover/cli/qa_cmd.py
gcover/cli/schema_cmd.py
gcover/cli/sde_cmd.py
gcover/core/__init__.py
gcover/core/config.py
gcover/manage/__init__py
gcover/qa/__init__.py
gcover/qa/lines_in_unco.py
gcover/schema/__init__.py
gcover/schema/differ.py
gcover/schema/extractor.py
gcover/schema/models.py
gcover/schema/reporter.py
gcover/schema/transformer.py
gcover/schema/utils.py
gcover/schema/exporters/__init__.py
gcover/schema/exporters/json.py
gcover/schema/exporters/plantuml.py
gcover/sde/__init__.py
gcover/sde/bridge.py
gcover/sde/connection_manager.py
gcover/sde/exceptions.py
gcover/utils/__init__.py
gcover/utils/decorators.py
gcover/utils/gpkg.py
gcover/utils/imports.py
lg_gcover-0.1.dev15.dist-info/licenses/LICENSE
lg_gcover-0.1.dev15.dist-info/METADATA
lg_gcover-0.1.dev15.dist-info/WHEEL
lg_gcover-0.1.dev15.dist-info/entry_points.txt
lg_gcover-0.1.dev15.dist-info/top_level.txt
lg_gcover-0.1.dev15.dist-info/RECORD
